{
  "team_info": {
    "school_id": "hunter",
    "school_name": "Hunter College",
    "abbreviation": "HUNT",
    "mascot": "Hawks",
    "conference": "Metro Atlantic",
    "city": "New York",
    "state": "NY",
    "colors": [
      "Purple",
      "Gold"
    ]
  },
  "identity": {
    "style": "conservative",
    "philosophy": "kick_heavy",
    "tempo": "fast",
    "two_way_emphasis": "medium"
  },
  "recruiting_pipeline": {
    "northeast": 0.5,
    "texas_southwest": 0.19,
    "west_coast": 0.09,
    "mid_atlantic": 0.05,
    "south": 0.04,
    "australian": 0.064,
    "canadian_french": 0.064
  },
  "roster": {
    "size": 38,
    "players": [
      {
        "number": 4,
        "name": "Sophia Silva",
        "position": "Back/Safety",
        "height": "5-7",
        "weight": 161,
        "year": "Senior",
        "hometown": {
          "city": "Washington",
          "state": "DC",
          "country": "USA",
          "region": "mid_atlantic"
        },
        "high_school": "Washington North High",
        "nationality": "American",
        "archetype": "return_keeper",
        "potential": 4,
        "development": "normal",
        "stats": {
          "speed": 67,
          "stamina": 54,
          "kicking": 66,
          "lateral_skill": 77,
          "tackling": 53,
          "agility": 82,
          "power": 61,
          "awareness": 83,
          "hands": 66,
          "kick_power": 62,
          "kick_accuracy": 60
        }
      },
      {
        "number": 9,
        "name": "Talia Stewart",
        "position": "Back/Corner",
        "height": "5-6",
        "weight": 174,
        "year": "Sophomore",
        "hometown": {
          "city": "Pittsburgh",
          "state": "PA",
          "country": "USA",
          "region": "northeast"
        },
        "high_school": "Pittsburgh High School",
        "nationality": "American",
        "archetype": "reliable_flanker",
        "potential": 3,
        "development": "quick",
        "stats": {
          "speed": 77,
          "stamina": 76,
          "kicking": 63,
          "lateral_skill": 65,
          "tackling": 72,
          "agility": 83,
          "power": 76,
          "awareness": 71,
          "hands": 72,
          "kick_power": 82,
          "kick_accuracy": 81
        }
      },
      {
        "number": 11,
        "name": "Cameron Santos",
        "position": "Wedge/Line",
        "height": "5-10",
        "weight": 202,
        "year": "Sophomore",
        "hometown": {
          "city": "Norfolk",
          "state": "VA",
          "country": "USA",
          "region": "mid_atlantic"
        },
        "high_school": "Norfolk West High",
        "nationality": "American",
        "archetype": "none",
        "potential": 2,
        "development": "normal",
        "stats": {
          "speed": 74,
          "stamina": 69,
          "kicking": 51,
          "lateral_skill": 59,
          "tackling": 67,
          "agility": 76,
          "power": 70,
          "awareness": 81,
          "hands": 62,
          "kick_power": 66,
          "kick_accuracy": 77
        }
      },
      {
        "number": 14,
        "name": "Penelope Gomez",
        "position": "Wedge/Line",
        "height": "5-11",
        "weight": 209,
        "year": "Freshman",
        "hometown": {
          "city": "Detroit",
          "state": "MI",
          "country": "USA",
          "region": "midwest"
        },
        "high_school": "Detroit West High",
        "nationality": "American",
        "archetype": "none",
        "potential": 2,
        "development": "normal",
        "stats": {
          "speed": 58,
          "stamina": 65,
          "kicking": 74,
          "lateral_skill": 63,
          "tackling": 72,
          "agility": 50,
          "power": 63,
          "awareness": 67,
          "hands": 71,
          "kick_power": 60,
          "kick_accuracy": 77
        }
      },
      {
        "number": 16,
        "name": "Diana Ford",
        "position": "Viper/Back",
        "height": "5-10",
        "weight": 177,
        "year": "Senior",
        "hometown": {
          "city": "Charlotte",
          "state": "NC",
          "country": "USA",
          "region": "south"
        },
        "high_school": "Charlotte High School",
        "nationality": "American",
        "archetype": "receiving_viper",
        "potential": 4,
        "development": "late_bloomer",
        "stats": {
          "speed": 77,
          "stamina": 76,
          "kicking": 78,
          "lateral_skill": 85,
          "tackling": 72,
          "agility": 83,
          "power": 58,
          "awareness": 65,
          "hands": 70,
          "kick_power": 72,
          "kick_accuracy": 50
        }
      },
      {
        "number": 17,
        "name": "Zara Graham",
        "position": "Shiftback/Back",
        "height": "5-9",
        "weight": 164,
        "year": "Sophomore",
        "hometown": {
          "city": "Houston",
          "state": "TX",
          "country": "USA",
          "region": "texas_southwest"
        },
        "high_school": "Houston High School",
        "nationality": "American",
        "archetype": "elusive_flanker",
        "potential": 3,
        "development": "normal",
        "stats": {
          "speed": 72,
          "stamina": 76,
          "kicking": 77,
          "lateral_skill": 81,
          "tackling": 62,
          "agility": 64,
          "power": 56,
          "awareness": 81,
          "hands": 57,
          "kick_power": 60,
          "kick_accuracy": 50
        }
      },
      {
        "number": 18,
        "name": "Nora White",
        "position": "Zeroback/Back",
        "height": "6-1",
        "weight": 189,
        "year": "Sophomore",
        "hometown": {
          "city": "Buffalo",
          "state": "NY",
          "country": "USA",
          "region": "northeast"
        },
        "high_school": "Buffalo High School",
        "nationality": "American",
        "archetype": "running_zb",
        "potential": 3,
        "development": "slow",
        "stats": {
          "speed": 79,
          "stamina": 67,
          "kicking": 58,
          "lateral_skill": 72,
          "tackling": 72,
          "agility": 53,
          "power": 60,
          "awareness": 81,
          "hands": 70,
          "kick_power": 65,
          "kick_accuracy": 87
        }
      },
      {
        "number": 19,
        "name": "Emily Gonzalez",
        "position": "Viper/Back",
        "height": "5-11",
        "weight": 173,
        "year": "Freshman",
        "hometown": {
          "city": "Boston",
          "state": "MA",
          "country": "USA",
          "region": "northeast"
        },
        "high_school": "Boston High School",
        "nationality": "American",
        "archetype": "hybrid_viper",
        "potential": 2,
        "development": "normal",
        "stats": {
          "speed": 72,
          "stamina": 63,
          "kicking": 82,
          "lateral_skill": 58,
          "tackling": 54,
          "agility": 56,
          "power": 66,
          "awareness": 58,
          "hands": 58,
          "kick_power": 66,
          "kick_accuracy": 83
        }
      },
      {
        "number": 20,
        "name": "Amelia Diaz",
        "position": "Back/Corner",
        "height": "6-0",
        "weight": 168,
        "year": "Junior",
        "hometown": {
          "city": "San Francisco",
          "state": "CA",
          "country": "USA",
          "region": "west_coast"
        },
        "high_school": "San Francisco High School",
        "nationality": "American",
        "archetype": "sure_hands_keeper",
        "potential": 3,
        "development": "normal",
        "stats": {
          "speed": 88,
          "stamina": 55,
          "kicking": 62,
          "lateral_skill": 68,
          "tackling": 57,
          "agility": 56,
          "power": 75,
          "awareness": 80,
          "hands": 61,
          "kick_power": 69,
          "kick_accuracy": 81
        }
      },
      {
        "number": 21,
        "name": "Aria Ellis",
        "position": "Lineman",
        "height": "6-0",
        "weight": 198,
        "year": "Senior",
        "hometown": {
          "city": "Kansas City",
          "state": "MO",
          "country": "USA",
          "region": "midwest"
        },
        "high_school": "Kansas City South High",
        "nationality": "American",
        "archetype": "none",
        "potential": 3,
        "development": "normal",
        "stats": {
          "speed": 70,
          "stamina": 61,
          "kicking": 81,
          "lateral_skill": 71,
          "tackling": 77,
          "agility": 70,
          "power": 62,
          "awareness": 72,
          "hands": 71,
          "kick_power": 79,
          "kick_accuracy": 81
        }
      },
      {
        "number": 24,
        "name": "Grace Mason",
        "position": "Wing/End",
        "height": "5-7",
        "weight": 173,
        "year": "Freshman",
        "hometown": {
          "city": "Buffalo",
          "state": "NY",
          "country": "USA",
          "region": "northeast"
        },
        "high_school": "Buffalo High School",
        "nationality": "American",
        "archetype": "speed_flanker",
        "potential": 3,
        "development": "normal",
        "stats": {
          "speed": 79,
          "stamina": 66,
          "kicking": 54,
          "lateral_skill": 63,
          "tackling": 64,
          "agility": 70,
          "power": 78,
          "awareness": 73,
          "hands": 66,
          "kick_power": 50,
          "kick_accuracy": 60
        }
      },
      {
        "number": 25,
        "name": "Julia Thompson",
        "position": "Lineman",
        "height": "6-0",
        "weight": 197,
        "year": "Freshman",
        "hometown": {
          "city": "Worcester",
          "state": "MA",
          "country": "USA",
          "region": "northeast"
        },
        "high_school": "Worcester East High",
        "nationality": "American",
        "archetype": "none",
        "potential": 3,
        "development": "normal",
        "stats": {
          "speed": 51,
          "stamina": 79,
          "kicking": 59,
          "lateral_skill": 59,
          "tackling": 68,
          "agility": 69,
          "power": 79,
          "awareness": 68,
          "hands": 82,
          "kick_power": 78,
          "kick_accuracy": 50
        }
      },
      {
        "number": 30,
        "name": "Rebecca Nguyen",
        "position": "Wedge/Line",
        "height": "6-2",
        "weight": 208,
        "year": "Freshman",
        "hometown": {
          "city": "Phoenix",
          "state": "AZ",
          "country": "USA",
          "region": "texas_southwest"
        },
        "high_school": "Phoenix High School",
        "nationality": "American",
        "archetype": "none",
        "potential": 5,
        "development": "normal",
        "stats": {
          "speed": 70,
          "stamina": 70,
          "kicking": 82,
          "lateral_skill": 53,
          "tackling": 64,
          "agility": 69,
          "power": 83,
          "awareness": 82,
          "hands": 81,
          "kick_power": 70,
          "kick_accuracy": 52
        }
      },
      {
        "number": 33,
        "name": "London Washington",
        "position": "Shiftback/Back",
        "height": "5-11",
        "weight": 182,
        "year": "Sophomore",
        "hometown": {
          "city": "Charleston",
          "state": "SC",
          "country": "USA",
          "region": "south"
        },
        "high_school": "Charleston High School",
        "nationality": "American",
        "archetype": "power_flanker",
        "potential": 4,
        "development": "normal",
        "stats": {
          "speed": 73,
          "stamina": 75,
          "kicking": 54,
          "lateral_skill": 70,
          "tackling": 66,
          "agility": 58,
          "power": 68,
          "awareness": 81,
          "hands": 60,
          "kick_power": 71,
          "kick_accuracy": 76
        }
      },
      {
        "number": 35,
        "name": "Elise Evans",
        "position": "Back/Safety",
        "height": "5-10",
        "weight": 155,
        "year": "Sophomore",
        "hometown": {
          "city": "Fresno",
          "state": "CA",
          "country": "USA",
          "region": "west_coast"
        },
        "high_school": "Fresno East High",
        "nationality": "American",
        "archetype": "tackle_keeper",
        "potential": 4,
        "development": "normal",
        "stats": {
          "speed": 83,
          "stamina": 81,
          "kicking": 69,
          "lateral_skill": 57,
          "tackling": 59,
          "agility": 63,
          "power": 82,
          "awareness": 68,
          "hands": 76,
          "kick_power": 81,
          "kick_accuracy": 67
        }
      },
      {
        "number": 36,
        "name": "Penelope Fox",
        "position": "Wing/End",
        "height": "5-7",
        "weight": 160,
        "year": "Senior",
        "hometown": {
          "city": "Burlington",
          "state": "VT",
          "country": "USA",
          "region": "northeast"
        },
        "high_school": "Burlington Academy",
        "nationality": "American",
        "archetype": "speed_flanker",
        "potential": 2,
        "development": "slow",
        "stats": {
          "speed": 72,
          "stamina": 82,
          "kicking": 54,
          "lateral_skill": 74,
          "tackling": 80,
          "agility": 72,
          "power": 80,
          "awareness": 55,
          "hands": 74,
          "kick_power": 77,
          "kick_accuracy": 50
        }
      },
      {
        "number": 39,
        "name": "Savannah Moore",
        "position": "Wing/End",
        "height": "5-11",
        "weight": 188,
        "year": "Sophomore",
        "hometown": {
          "city": "Providence",
          "state": "RI",
          "country": "USA",
          "region": "northeast"
        },
        "high_school": "Providence High School",
        "nationality": "American",
        "archetype": "elusive_flanker",
        "potential": 2,
        "development": "normal",
        "stats": {
          "speed": 60,
          "stamina": 61,
          "kicking": 57,
          "lateral_skill": 58,
          "tackling": 61,
          "agility": 56,
          "power": 53,
          "awareness": 83,
          "hands": 88,
          "kick_power": 80,
          "kick_accuracy": 54
        }
      },
      {
        "number": 41,
        "name": "Clara Martin",
        "position": "Wing/End",
        "height": "5-11",
        "weight": 194,
        "year": "Freshman",
        "hometown": {
          "city": "Portland",
          "state": "ME",
          "country": "USA",
          "region": "northeast"
        },
        "high_school": "Portland South High",
        "nationality": "American",
        "archetype": "reliable_flanker",
        "potential": 2,
        "development": "normal",
        "stats": {
          "speed": 81,
          "stamina": 54,
          "kicking": 57,
          "lateral_skill": 53,
          "tackling": 68,
          "agility": 81,
          "power": 74,
          "awareness": 54,
          "hands": 59,
          "kick_power": 72,
          "kick_accuracy": 51
        }
      },
      {
        "number": 46,
        "name": "Valeria Sanders",
        "position": "Back/Corner",
        "height": "5-6",
        "weight": 184,
        "year": "Junior",
        "hometown": {
          "city": "Denver",
          "state": "CO",
          "country": "USA",
          "region": "texas_southwest"
        },
        "high_school": "Denver North High",
        "nationality": "American",
        "archetype": "sure_hands_keeper",
        "potential": 2,
        "development": "quick",
        "stats": {
          "speed": 82,
          "stamina": 71,
          "kicking": 57,
          "lateral_skill": 55,
          "tackling": 79,
          "agility": 78,
          "power": 82,
          "awareness": 75,
          "hands": 67,
          "kick_power": 54,
          "kick_accuracy": 77
        }
      },
      {
        "number": 53,
        "name": "Grace Jensen",
        "position": "Shiftback/Back",
        "height": "5-11",
        "weight": 165,
        "year": "Junior",
        "hometown": {
          "city": "Rochester",
          "state": "NY",
          "country": "USA",
          "region": "northeast"
        },
        "high_school": "Rochester High School",
        "nationality": "American",
        "archetype": "reliable_flanker",
        "potential": 2,
        "development": "normal",
        "stats": {
          "speed": 73,
          "stamina": 67,
          "kicking": 68,
          "lateral_skill": 54,
          "tackling": 55,
          "agility": 83,
          "power": 56,
          "awareness": 64,
          "hands": 68,
          "kick_power": 77,
          "kick_accuracy": 58
        }
      },
      {
        "number": 55,
        "name": "Paloma Edwards",
        "position": "Back/Safety",
        "height": "6-0",
        "weight": 164,
        "year": "Junior",
        "hometown": {
          "city": "Charlotte",
          "state": "NC",
          "country": "USA",
          "region": "south"
        },
        "high_school": "Charlotte South High",
        "nationality": "American",
        "archetype": "tackle_keeper",
        "potential": 3,
        "development": "normal",
        "stats": {
          "speed": 87,
          "stamina": 67,
          "kicking": 65,
          "lateral_skill": 71,
          "tackling": 66,
          "agility": 60,
          "power": 72,
          "awareness": 60,
          "hands": 70,
          "kick_power": 58,
          "kick_accuracy": 78
        }
      },
      {
        "number": 56,
        "name": "Megan Russell",
        "position": "Back/Corner",
        "height": "5-11",
        "weight": 184,
        "year": "Sophomore",
        "hometown": {
          "city": "Detroit",
          "state": "MI",
          "country": "USA",
          "region": "midwest"
        },
        "high_school": "Detroit High School",
        "nationality": "American",
        "archetype": "return_keeper",
        "potential": 2,
        "development": "normal",
        "stats": {
          "speed": 84,
          "stamina": 56,
          "kicking": 71,
          "lateral_skill": 72,
          "tackling": 67,
          "agility": 63,
          "power": 70,
          "awareness": 56,
          "hands": 79,
          "kick_power": 76,
          "kick_accuracy": 59
        }
      },
      {
        "number": 57,
        "name": "Sierra Powell",
        "position": "Back/Corner",
        "height": "5-7",
        "weight": 183,
        "year": "Freshman",
        "hometown": {
          "city": "Burlington",
          "state": "VT",
          "country": "USA",
          "region": "northeast"
        },
        "high_school": "Burlington High School",
        "nationality": "American",
        "archetype": "reliable_flanker",
        "potential": 2,
        "development": "slow",
        "stats": {
          "speed": 53,
          "stamina": 77,
          "kicking": 57,
          "lateral_skill": 74,
          "tackling": 57,
          "agility": 67,
          "power": 70,
          "awareness": 62,
          "hands": 65,
          "kick_power": 76,
          "kick_accuracy": 60
        }
      },
      {
        "number": 62,
        "name": "Juliana Russell",
        "position": "Back/Corner",
        "height": "5-9",
        "weight": 182,
        "year": "Freshman",
        "hometown": {
          "city": "Miami",
          "state": "FL",
          "country": "USA",
          "region": "south"
        },
        "high_school": "Miami East High",
        "nationality": "American",
        "archetype": "tackle_keeper",
        "potential": 4,
        "development": "normal",
        "stats": {
          "speed": 61,
          "stamina": 80,
          "kicking": 62,
          "lateral_skill": 54,
          "tackling": 64,
          "agility": 81,
          "power": 70,
          "awareness": 83,
          "hands": 54,
          "kick_power": 50,
          "kick_accuracy": 83
        }
      },
      {
        "number": 69,
        "name": "Alexandra Jordan",
        "position": "Wedge/Line",
        "height": "6-1",
        "weight": 198,
        "year": "Junior",
        "hometown": {
          "city": "St. Louis",
          "state": "MO",
          "country": "USA",
          "region": "midwest"
        },
        "high_school": "St. Louis Prep",
        "nationality": "American",
        "archetype": "none",
        "potential": 2,
        "development": "late_bloomer",
        "stats": {
          "speed": 63,
          "stamina": 74,
          "kicking": 59,
          "lateral_skill": 68,
          "tackling": 62,
          "agility": 60,
          "power": 75,
          "awareness": 65,
          "hands": 79,
          "kick_power": 71,
          "kick_accuracy": 74
        }
      },
      {
        "number": 70,
        "name": "Ada Collins",
        "position": "Zeroback/Back",
        "height": "5-7",
        "weight": 168,
        "year": "Senior",
        "hometown": {
          "city": "Columbus",
          "state": "OH",
          "country": "USA",
          "region": "midwest"
        },
        "high_school": "Columbus North High",
        "nationality": "American",
        "archetype": "dual_threat_zb",
        "potential": 3,
        "development": "normal",
        "stats": {
          "speed": 79,
          "stamina": 80,
          "kicking": 82,
          "lateral_skill": 81,
          "tackling": 78,
          "agility": 75,
          "power": 72,
          "awareness": 82,
          "hands": 66,
          "kick_power": 87,
          "kick_accuracy": 59
        }
      },
      {
        "number": 71,
        "name": "Layla Jensen",
        "position": "Shiftback/Back",
        "height": "5-7",
        "weight": 177,
        "year": "Freshman",
        "hometown": {
          "city": "Louisville",
          "state": "KY",
          "country": "USA",
          "region": "south"
        },
        "high_school": "Louisville Prep",
        "nationality": "American",
        "archetype": "power_flanker",
        "potential": 2,
        "development": "normal",
        "stats": {
          "speed": 85,
          "stamina": 61,
          "kicking": 66,
          "lateral_skill": 87,
          "tackling": 71,
          "agility": 76,
          "power": 54,
          "awareness": 54,
          "hands": 71,
          "kick_power": 78,
          "kick_accuracy": 71
        }
      },
      {
        "number": 72,
        "name": "Quinn Lopez",
        "position": "Wedge/Line",
        "height": "5-10",
        "weight": 206,
        "year": "Freshman",
        "hometown": {
          "city": "Buffalo",
          "state": "NY",
          "country": "USA",
          "region": "northeast"
        },
        "high_school": "Buffalo High School",
        "nationality": "American",
        "archetype": "none",
        "potential": 4,
        "development": "quick",
        "stats": {
          "speed": 69,
          "stamina": 72,
          "kicking": 51,
          "lateral_skill": 81,
          "tackling": 68,
          "agility": 82,
          "power": 82,
          "awareness": 53,
          "hands": 68,
          "kick_power": 77,
          "kick_accuracy": 80
        }
      },
      {
        "number": 73,
        "name": "Layla McCarthy",
        "position": "Wingback/End",
        "height": "5-10",
        "weight": 176,
        "year": "Freshman",
        "hometown": {
          "city": "Kansas City",
          "state": "MO",
          "country": "USA",
          "region": "midwest"
        },
        "high_school": "Kansas City High School",
        "nationality": "American",
        "archetype": "reliable_flanker",
        "potential": 3,
        "development": "normal",
        "stats": {
          "speed": 56,
          "stamina": 73,
          "kicking": 68,
          "lateral_skill": 71,
          "tackling": 58,
          "agility": 71,
          "power": 54,
          "awareness": 74,
          "hands": 71,
          "kick_power": 50,
          "kick_accuracy": 66
        }
      },
      {
        "number": 83,
        "name": "Jasmine King",
        "position": "Halfback/Back",
        "height": "5-11",
        "weight": 158,
        "year": "Junior",
        "hometown": {
          "city": "Los Angeles",
          "state": "CA",
          "country": "USA",
          "region": "west_coast"
        },
        "high_school": "Los Angeles High School",
        "nationality": "American",
        "archetype": "elusive_flanker",
        "potential": 4,
        "development": "normal",
        "stats": {
          "speed": 64,
          "stamina": 82,
          "kicking": 71,
          "lateral_skill": 76,
          "tackling": 57,
          "agility": 74,
          "power": 67,
          "awareness": 64,
          "hands": 78,
          "kick_power": 59,
          "kick_accuracy": 64
        }
      },
      {
        "number": 84,
        "name": "Rachel Black",
        "position": "Back/Corner",
        "height": "6-0",
        "weight": 170,
        "year": "Sophomore",
        "hometown": {
          "city": "Raleigh",
          "state": "NC",
          "country": "USA",
          "region": "south"
        },
        "high_school": "Raleigh Academy",
        "nationality": "American",
        "archetype": "tackle_keeper",
        "potential": 2,
        "development": "normal",
        "stats": {
          "speed": 79,
          "stamina": 77,
          "kicking": 65,
          "lateral_skill": 60,
          "tackling": 74,
          "agility": 67,
          "power": 76,
          "awareness": 73,
          "hands": 58,
          "kick_power": 61,
          "kick_accuracy": 70
        }
      },
      {
        "number": 85,
        "name": "Elena Shah",
        "position": "Back/Safety",
        "height": "5-10",
        "weight": 162,
        "year": "Junior",
        "hometown": {
          "city": "Annapolis",
          "state": "MD",
          "country": "USA",
          "region": "mid_atlantic"
        },
        "high_school": "Annapolis High School",
        "nationality": "American",
        "archetype": "reliable_flanker",
        "potential": 2,
        "development": "slow",
        "stats": {
          "speed": 77,
          "stamina": 74,
          "kicking": 75,
          "lateral_skill": 65,
          "tackling": 68,
          "agility": 61,
          "power": 57,
          "awareness": 69,
          "hands": 80,
          "kick_power": 75,
          "kick_accuracy": 50
        }
      },
      {
        "number": 87,
        "name": "Kamila Ward",
        "position": "Viper/Back",
        "height": "5-10",
        "weight": 184,
        "year": "Junior",
        "hometown": {
          "city": "Vancouver",
          "state": "BC",
          "country": "Canada",
          "region": "canadian_english"
        },
        "high_school": "Vancouver South High",
        "nationality": "Canadian",
        "archetype": "receiving_viper",
        "potential": 4,
        "development": "quick",
        "stats": {
          "speed": 70,
          "stamina": 63,
          "kicking": 61,
          "lateral_skill": 70,
          "tackling": 78,
          "agility": 56,
          "power": 61,
          "awareness": 73,
          "hands": 71,
          "kick_power": 73,
          "kick_accuracy": 77
        }
      },
      {
        "number": 88,
        "name": "Esmeralda Walsh",
        "position": "Back/Corner",
        "height": "5-6",
        "weight": 181,
        "year": "Junior",
        "hometown": {
          "city": "Memphis",
          "state": "TN",
          "country": "USA",
          "region": "south"
        },
        "high_school": "Memphis Academy",
        "nationality": "American",
        "archetype": "return_keeper",
        "potential": 2,
        "development": "normal",
        "stats": {
          "speed": 57,
          "stamina": 53,
          "kicking": 66,
          "lateral_skill": 56,
          "tackling": 69,
          "agility": 56,
          "power": 74,
          "awareness": 67,
          "hands": 64,
          "kick_power": 62,
          "kick_accuracy": 66
        }
      },
      {
        "number": 93,
        "name": "Sierra James",
        "position": "Halfback/Back",
        "height": "5-9",
        "weight": 176,
        "year": "Freshman",
        "hometown": {
          "city": "San Diego",
          "state": "CA",
          "country": "USA",
          "region": "west_coast"
        },
        "high_school": "San Diego High School",
        "nationality": "American",
        "archetype": "power_flanker",
        "potential": 4,
        "development": "normal",
        "stats": {
          "speed": 64,
          "stamina": 81,
          "kicking": 56,
          "lateral_skill": 75,
          "tackling": 58,
          "agility": 61,
          "power": 62,
          "awareness": 67,
          "hands": 74,
          "kick_power": 52,
          "kick_accuracy": 77
        }
      },
      {
        "number": 95,
        "name": "Zuri Murphy",
        "position": "Wingback/End",
        "height": "6-0",
        "weight": 184,
        "year": "Freshman",
        "hometown": {
          "city": "Boston",
          "state": "MA",
          "country": "USA",
          "region": "northeast"
        },
        "high_school": "Boston High School",
        "nationality": "American",
        "archetype": "reliable_flanker",
        "potential": 3,
        "development": "normal",
        "stats": {
          "speed": 74,
          "stamina": 54,
          "kicking": 61,
          "lateral_skill": 83,
          "tackling": 79,
          "agility": 61,
          "power": 58,
          "awareness": 67,
          "hands": 57,
          "kick_power": 79,
          "kick_accuracy": 60
        }
      },
      {
        "number": 97,
        "name": "Clara Webb",
        "position": "Wedge/Line",
        "height": "5-10",
        "weight": 186,
        "year": "Freshman",
        "hometown": {
          "city": "Portland",
          "state": "OR",
          "country": "USA",
          "region": "west_coast"
        },
        "high_school": "Portland North High",
        "nationality": "American",
        "archetype": "none",
        "potential": 3,
        "development": "normal",
        "stats": {
          "speed": 54,
          "stamina": 55,
          "kicking": 64,
          "lateral_skill": 77,
          "tackling": 72,
          "agility": 50,
          "power": 73,
          "awareness": 57,
          "hands": 73,
          "kick_power": 50,
          "kick_accuracy": 50
        }
      },
      {
        "number": 99,
        "name": "Savannah Adams",
        "position": "Lineman",
        "height": "5-10",
        "weight": 202,
        "year": "Senior",
        "hometown": {
          "city": "Burlington",
          "state": "VT",
          "country": "USA",
          "region": "northeast"
        },
        "high_school": "Burlington West High",
        "nationality": "American",
        "archetype": "none",
        "potential": 3,
        "development": "normal",
        "stats": {
          "speed": 64,
          "stamina": 53,
          "kicking": 72,
          "lateral_skill": 83,
          "tackling": 80,
          "agility": 78,
          "power": 61,
          "awareness": 71,
          "hands": 70,
          "kick_power": 70,
          "kick_accuracy": 69
        }
      }
    ]
  },
  "team_stats": {
    "avg_speed": 71,
    "avg_weight": 181,
    "avg_stamina": 68,
    "kicking_strength": 65,
    "lateral_proficiency": 68,
    "defensive_strength": 67
  },
  "coaching": {
    "head_coach": "Donna Reed",
    "head_coach_gender": "female",
    "philosophy": "Up-tempo chaos with creative schemes",
    "coaching_style": "innovative",
    "experience": "6 years",
    "background": "Long-time coordinator stepping into head role"
  }
}